Metadata-Version: 1.1
Name: deadoralive
Version: 0.1.0
Summary: A broken link checker service
Home-page: https://github.com/ckan/deadoralive
Author: Sean Hammond
Author-email: deadoralive@seanh.cc
License: AGPL
Keywords: ckan
Platform: UNKNOWN
Classifier: Development Status :: 4 - Beta
Classifier: Intended Audience :: Other Audience
Classifier: Topic :: Internet :: WWW/HTTP :: Site Management :: Link Checking
Classifier: License :: OSI Approved :: GNU Affero General Public License v3 or later (AGPLv3+)
Classifier: Programming Language :: Python :: 2.6
Classifier: Programming Language :: Python :: 2.7
